Easy_AI/__init__.py
Easy_AI/example.py
Easy_AI/exampleGTTs.py
Easy_AI-1.0.1.3.dist-info/LICENSE
Easy_AI-1.0.1.3.dist-info/METADATA
Easy_AI-1.0.1.3.dist-info/WHEEL
Easy_AI-1.0.1.3.dist-info/top_level.txt
Easy_AI-1.0.1.3.dist-info/RECORD
