Metadata-Version: 2.1
Name: Easy-AI
Version: 1.0.1.3
Summary: My Project Dont Touch
Home-page: UNKNOWN
Author: Khoa1468
Author-email: khoalam1468@gmail.com
License: UNKNOWN
Platform: UNKNOWN
License-File: LICENSE
Requires-Dist: pyttsx3
Requires-Dist: SpeechRecognition
Requires-Dist: gtts
Requires-Dist: playsound
